preprocessinglib_tonga_gumustakim/CategoricalEncoder.py
preprocessinglib_tonga_gumustakim/DataTypeConverter.py
preprocessinglib_tonga_gumustakim/DateTimeHandler.py
preprocessinglib_tonga_gumustakim/FeatureEngineer.py
preprocessinglib_tonga_gumustakim/MissingValueHandler.py
preprocessinglib_tonga_gumustakim/OutlierHandler.py
preprocessinglib_tonga_gumustakim/Scaler.py
preprocessinglib_tonga_gumustakim/TestDataPreprocessing.py
preprocessinglib_tonga_gumustakim/TextCleaner.py
preprocessinglib_tonga_gumustakim/__init__.py
preprocessinglib_tonga_gumustakim-0.5.dist-info/METADATA
preprocessinglib_tonga_gumustakim-0.5.dist-info/WHEEL
preprocessinglib_tonga_gumustakim-0.5.dist-info/top_level.txt
preprocessinglib_tonga_gumustakim-0.5.dist-info/RECORD
