Metadata-Version: 2.1
Name: preprocessinglib_tonga_gumustakim
Version: 0.5
Summary: A comprehensive data preprocessing library for Python
Home-page: https://github.com/Fzehzeh/mypreprocessinglib , https://github.com/ayserragm/mypreprocessinglib
Author: Zehra Tonga-Ayse Serra Gumustakim
Author-email: tongafatmazehra@gmail.com-ayseserra.gumustakim@stu.fsm.edu.tr 
Classifier: Programming Language :: Python :: 3
Classifier: License :: OSI Approved :: MIT License
Classifier: Operating System :: OS Independent
Requires-Python: >=3.6
Requires-Dist: pandas
Requires-Dist: numpy
Requires-Dist: scikit-learn
Requires-Dist: nltk
